contensis_management/__init__.py
contensis_management/api_client.py
contensis_management/api_response.py
contensis_management/api_response_abc.py
contensis_management/logging_config.py
contensis_management/lower_key_dict.py
contensis_management/request_handler.py
contensis_management/request_handler_abc.py
contensis_management/models/__init__.py
contensis_management/models/camel_case.py
contensis_management/models/group.py
contensis_management/models/message.py
contensis_management/models/page_options.py
contensis_management/models/paged_list.py
contensis_management/models/project.py
contensis_management/models/security_list_options.py
contensis_management/models/user.py
contensis_management/resource_handlers/__init__.py
contensis_management/resource_handlers/groups.py
contensis_management/resource_handlers/projects.py
contensis_management/resource_handlers/users.py
helpers/__init__.py
helpers/helper_config.py
helpers/mock_api_response.py
models/__init__.py
models/message_test.py
models/page_options_test.py
models/paged_list_test.py
models/project_test.py
models/security_list_options_test.py
models/user_test.py
resource_handlers/__init__.py
resource_handlers/projects_test.py
resource_handlers/users_test.py
contensis_management-0.0.1.dist-info/LICENSE
contensis_management-0.0.1.dist-info/METADATA
contensis_management-0.0.1.dist-info/WHEEL
contensis_management-0.0.1.dist-info/top_level.txt
contensis_management-0.0.1.dist-info/RECORD
