Metadata-Version: 2.2
Name: contensis_management
Version: 0.0.1
Summary: Contensis Management API
Author-email: Joe Collins <j.collins@zengenti.com>
Project-URL: homepage, https://github.com/zengenti/contensis-management-api-python
Project-URL: repository, https://github.com/zengenti/contensis-management-api-python
Project-URL: documentation, https://github.com/zengenti/contensis-management-api-python
Classifier: Programming Language :: Python :: 3
Classifier: Development Status :: 1 - Planning
Classifier: License :: OSI Approved :: MIT License
Classifier: Operating System :: OS Independent
Requires-Python: >=3.10
License-File: LICENSE
Requires-Dist: httpx
Requires-Dist: requests
Provides-Extra: dev
Requires-Dist: black; extra == "dev"
Requires-Dist: debugpy; extra == "dev"
Requires-Dist: python-dotenv; extra == "dev"
Requires-Dist: ipykernel; extra == "dev"
Requires-Dist: mypy; extra == "dev"
Requires-Dist: pre-commit; extra == "dev"
Requires-Dist: pydantic; extra == "dev"
Requires-Dist: pytest; extra == "dev"
Requires-Dist: pytest-cov; extra == "dev"
Requires-Dist: ruff; extra == "dev"
Requires-Dist: sourcery; extra == "dev"
Requires-Dist: types-requests; extra == "dev"
